CHANGELOG.md
LICENSE
README.md
automationhat/__init__.py
automationhat/pins.py
automationhat-1.0.0.dist-info/METADATA
automationhat-1.0.0.dist-info/WHEEL
automationhat-1.0.0.dist-info/licenses/LICENSE
automationhat-1.0.0.dist-info/RECORD
