Metadata-Version: 2.3
Name: automationhat
Version: 1.0.0
Summary: Driver for the Pimoroni Automation HAT
Project-URL: GitHub, https://www.github.com/pimoroni/automationhat-python
Project-URL: Homepage, https://www.pimoroni.com
Author-email: Philip Howard <phil@pimoroni.com>
Maintainer-email: Philip Howard <phil@pimoroni.com>
License: MIT License
License-File: LICENSE
Keywords: Pi,Raspberry,automation controller
Classifier: Development Status :: 4 - Beta
Classifier: Intended Audience :: Developers
Classifier: License :: OSI Approved :: MIT License
Classifier: Operating System :: POSIX :: Linux
Classifier: Programming Language :: Python :: 3
Classifier: Programming Language :: Python :: 3 :: Only
Classifier: Programming Language :: Python :: 3.7
Classifier: Programming Language :: Python :: 3.8
Classifier: Programming Language :: Python :: 3.9
Classifier: Programming Language :: Python :: 3.10
Classifier: Programming Language :: Python :: 3.11
Classifier: Topic :: Software Development
Classifier: Topic :: Software Development :: Libraries
Classifier: Topic :: System :: Hardware
Requires-Python: >=3.7
Requires-Dist: ads1015>=1.0.0
Requires-Dist: gpiod>=2.1.3
Requires-Dist: gpiodevice>=0.0.5
Requires-Dist: sn3218>=3.0.0
Requires-Dist: st7735>=1.0.0
